{
  "source_id": "horsley_china_corporate_social_credit_1-31-20",
  "source_file": "horsley_china_corporate_social_credit_1-31-20.txt",
  "chunk_index": 7,
  "char_count": 2990,
  "text": "Administrative licensing 行政许可\n           Various licenses and approvals from different authorities required to do business in China, and their revocation\n                                               Administrative punishment 行政处罚\n                                               Records of administrative punishments\n                     Priority Watch 重点关注 OR Abnormal Operations Information列入经营异常名录信息\nRecords of abnormal operations 异常经营 include failure of compliance with government disclosure as well as with other regulations\n\nInformation on incentives for trustworthiness 守信激励\n                   Such as “A-level taxpayer”\n                            (Redlists)\n\nPunishments for untrustworthiness 失信惩戒 (Blacklist)                    Information on Serious Illegal and Untrustworthy Acts\n  (Cause of punishment includes delay of salary payment to                                    (Blacklist)\n employees, delay on the enforcement of court decisions, etc.)               列入严重违法失信企业名单（黑名单）信息\n                    Qualifications 资质资格\n                    Risk warnings 风险提示\n                           Other 其它\n\nComprehensive Credit Assessments (公共信用综合评价）\n    • September 2019 NDRC announced comprehensive public credit\n      appraisals of 33 million companies on trial basis\n            • To be sent to provincial government for inclusion in provincial credit\n              information sharing platforms and for distribution to departments and lower\n              government levels\n            • To be included as an important part of companies' credit information\n            • To be used “for reference” and combined with industry, local public\n              comprehensive, and market (3d party credit service entities) credit appraisal\n              results\n            • In support of hierarchical and categorical regulation (分级分类监管):\n              lighter regulation for compliant, stricter regulation for non-compliant\n    • Companies to be classified/graded as excellent (优), good (良), average (中)\n        or poor (差)\n           • Excellent and good companies encouraged to further improve credit profile;\n             average advised how to improve; poor informed of non-compliant conduct,\n             how to repair credit, with advice recorded in credit record and NCISP\n    • Provinces to collect suggestions and feedback on the pilot appraisal\n      methodology and report back to NDRC Finance Dep’t and NPCIC\n                                                                                                                               20\n\n10\n\f                                                                                     1/31/2020\n\nHow does SCS apply to FIEs?\n• Foreign Investment Law (FIL), its Implementing Regulations and\n  MOFCOM Reporting Measures for Foreign Invested Enterprises (FIEs)\n  call for reporting of investment information, including annual reports,\n  through SAMR’s online Enterprise Registration System [企业登记系统],\n  http://wsdj.samr.gov.cn, and NECIPS"
}