{
  "source_id": "journal_pone_0318328",
  "source_file": "journal.pone.0318328.txt",
  "chunk_index": 46,
  "char_count": 1711,
  "text": "Heterogeneity of regional financial development\n                                           Regions with high financial development are rich in resources, efficient in allocation, and\n                                           mature in various financial policies and regulations, providing favorable support for the\n                                           improvement of enterprise information disclosure systems and promoting investment effi-\n                                           ciency. By referring to existing research [56], this study adopts the ratio of the total balance of\n                                           deposits and loans of financial institutions in various places at the end of the year to the gross\n                                           regional product to measure the regional financial development level. Samples larger than the\n                                           average value are divided into groups with good regional financial development, and samples\n                                           smaller than the average value are divided into groups with poor regional financial\n                                           development.\n                                              It can be seen that the coefficient of TREAT×POST is only significant in Column (5) in\n                                           Table 8 (Panel A), which means that in areas with good financial development levels, the social\n                                           credit system construction has a more obvious role. Here, the social credit system construction\n                                           can reduce 0.426% of enterprises’ overinvestment at the average level."
}