{
  "source_id": "Chinas_Corporate_Social_Credit_System",
  "source_file": "Chinas_Corporate_Social_Credit_System.txt",
  "chunk_index": 113,
  "char_count": 2898,
  "text": "5 Samantha Hoffman, “Social Credit,” Australian Strategic Policy Institute, June 2018. https://www.aspi.org.au/\n                   report/social-credit.\n\n6 Larry Catá Backer, “China’s Social Credit System: Data-Driven Governance For a ‘New Era’,” Current History\n                   Volume 118:809 (January 2019): 209-214.\n\n7 Third Plenary Session of the Eighteenth Central Committee of the Communist Party of China, “Decision of\n                   the Central Committee of the Communist Party of China on Several Major Issues in Comprehensively Deepening\n                   Reform”, November 12, 2013. http://webcache.googleusercontent.com/search?q=cache:MvxDJ0OopCkJ:www.gov.\n                   cn/jrzg/2013-11/15/content_2528179.htm+&cd=1&hl=en&ct=clnk&gl=ph.\n\n8 General Office of the State Council of the People’s Republic of China, “Li Keqiang chaired an Executive\n                   Meeting of the State Council (January 15, 2014)” ( 李克强主持召开国务院常务会议(2014年1月15日)), Janu-\n                   ary 15, 2014. Translation. http://webcache.googleusercontent.com/search?q=cache:http://www.gov.cn/guowuyu-\n                   an/2014-01/15/content_2591053.htm.\n\n9 Lin Junyue, Principles of the Social Credit System (社会信用体系原理), China Fangzheng Press, December\n                   2002. Translation.\n\n10 Lin Junyue, “Why Do We Say the Construction of the Social Credit System Began in 1999?” (林钧跃：为什\n                   么说社会信用体系建设起始于1999年?), Xinhua Credit, September 9, 2019. Translation. http://webcache.google-\n                   usercontent.com/search?q=cache:https://m.credit100.com/xhxy/c/2019-09-09/535610.shtml.\n\n11 Yu Jinming, Lin Junyue & Sun Jie, The National Credit Management System (国家信用管理体系), Social\n                   Sciences Academic Press, March 2000. Translation.\n\n12 Lin Junyue, “Credit Concepts” (信用概念) in Principles of the Social Credit System, China Fangzheng Press,\n                   January December 2002, 2-24. Translation.\n\n13 Lin Junyue, Principles of the Social Credit System (社会信用体系原理), China Fangzheng Press, December\n                   2002. Translation.\n\n14 Lin Junyue, Principles of the Social Credit System (社会信用体系原理), China Fangzheng Press, December\n                   2002.;Wu Weihai and Zhang Shaoli, Credit of Great Powers: the Global Vision of China’s Social Credit System (大\n                   国信用 全球视野的中国社会信用体系), China Planning Press, January 2017. Translation.\ntriviumchina.com\n\n15 Lin Junyue, Principles of the Social Credit System (社会信用体系原理), China Fangzheng Press, December\n                   2002, 50. Translation.\n\n77\n\f                   References & Notes\n\n16 Lin Junyue, “Legal Environment for the Establishment of a Credit System” (建立信用体系的法律环境) in\n\nChina’s Corporate Social Credit System - Context, Competition, Technology and Geopolitics\n                   Principles of the Social Credit System, China Fangzheng Press, December 2002, 140-165. Translation."
}