{
  "source_id": "Chinas_Corporate_Social_Credit_System",
  "source_file": "Chinas_Corporate_Social_Credit_System.txt",
  "chunk_index": 62,
  "char_count": 2417,
  "text": "More recently, throughout the 2018-2020 time period, the central government has\n                   repeatedly urged banks to increase lending to small and micro-enterprises,142 and relatedly, officials\n                   have attempted to leverage CSCS data to ameliorate the lack of risk assessment metrics through a\n                   joint NDRC and China Banking and Insurance Regulatory Commission (CBIRC) initiative called\n                   Xinyidai (信易贷).143 Xinyidai encourages the development of PCI-based financial risk assessment\n                   models specifically aimed at enabling SME loans. These models have been developed both by the\n                   central government as a service to banks and lenders and by banks and other lenders themselves,\n                   with the hope that access to such risk assessments will make lending to SMEs both more viable\n                   and financially attractive.\n\n6.2 The corporate bond market and credit ratings\n                           In addition to the weaknesses in China’s credit assessment mechanisms that have held back\n                   bank lending and other forms of indirect financing to private companies and SMEs, unreliable\n                   corporate bond ratings have also held back development of the bond market and a commensurate\n                   increase in direct financing for private companies.144 Specifically, tight state control over the\n                   corporate bond market has resulted in a disempowered, corrupt ratings industry whose ratings have\n                   historically been seen as largely ornamental:\n\nChinese credit rating agencies (CRAs) are a direct product of Chinese regulators’\n                            mandate that all public bonds have to be rated. With a regulatory captive customer\n                            base, the Chinese rating industry, as a whole, has less incentive and pressure to\n                            provide a high-quality product: informative credit ratings. Furthermore, there is a\n                            generally negative perception of the quality of Chinese bond ratings. The fact that\n                            the vast majority of Chinese bonds are rated AA or better has raised doubts about\n                            the accuracy of Chinese ratings and concerns of over-optimism of Chinese CRAs\n                            and/or rating shopping.145"
}