{
  "source_id": "report_201701",
  "source_file": "report_201701.txt",
  "chunk_index": 34,
  "char_count": 2978,
  "text": "先 使 用 者 は 相 手 方 の 商 標 に 対 し て 知 名 度 調 査 を 行 う こ と が で き 、商 標 権\n者に対して、同時に先使用の証拠を提出するよう求めることができる。\n係争商標の知名度が低く、使用地域が限られ、又は実際に使用していな\n\nい場合は、先行権利者の抗弁主張に有利である。これに対し、先使用者\nは 、設 計 と 関 係 商 標 の 使 用 に 関 す る 趣 旨 と 商 標 の 由 来 を 立 証 し て 説 明 で\nきる。\n\n6 )「 ピ カ ソ 」商 標 使 用 許 可 契 約 事 件 ( 上 海 市 高 級 人 民 法 院 ( 2014 )滬 高 民\n\n三 (知 ) 終 字 第 117 号 民 事 判 決 書 )\n\n事件の概要\n\n75\n\f  畢 加 索 国 際 企 業 股 份 有 限 公 司 (以 下「 畢 加 索 社 」と い う ) は 、\n                                                     「         」\n図 形 商 標 (以 下「 係 争 商 標 」と い う ) の 商 標 権 者 で あ る 。2 008 年 9 月 8 日 、\n\n畢 加 索 社 は 、 上 海 帕 弗 洛 文 化 用 品 有 限 公 司 (以 下 「 帕 弗 洛 社 」 と い う )に\n\n対 し 、中 国 大 陸 地 区 に お け る 筆 記 用 具 類 別 上 の 係 争 商 標 の 独 占 使 用 を 許\n諾 し た が 、 そ の 期 限 は 2008 年 9 月 10 日 ～ 2013 年 12 月 31 日 で あ っ た 。\n\n2009 年 3 月 12 日 、 当 該 商 標 の 使 用 許 諾 契 約 の 届 出 は 、 国 家 工 商 総 局 商\n\n標 局 の 許 可 を 取 得 し た 。 2010 年 2 月 11 日 、 畢 加 索 社 と 帕 弗 洛 社 は 、 商\n標 の 使 用 許 諾 期 限 に つ い て 原 契 約 を 基 に し て 10 年 間 延 長 す る こ と を 約\n定 し た 。2012 年 1 月 1 日 、畢 加 索 社 と 帕 弗 洛 社 は 、双 方 間 の 係 争 商 標 の\n\n使 用 許 諾 届 出 を 終 止 す る こ と を 約 定 し た も の の 、当 該 商 標 の そ の 他 の 約\n定 に 対 し て は 影 響 を 与 え な い も の と し た 。 2012 年 2 月 16 日 、 畢 加 索 社\nと 上 海 芸 想 文 化 用 品 有 限 公 司 (以 下「 芸 想 社 」と い う )と は 、\n                                                  「商標使用許\n\n諾 契 約 書 」(以 下「 係 争 契 約 」と い う )を 締 結 し 、芸 想 社 が 2012 年 1 月 15\n日 ～ 2017 年 8 月 31 日 ま で の 期 間 に お い て 独 占 的 に 係 争 商 標 を 使 用 す る\nことを約定した。帕弗洛社は、畢加索社と芸想社との間の行為が「契約\n法 」に 規 定 す る「 悪 意 で 気 脈 を 通 じ 合 っ て 第 三 者 の 合 法 的 利 益 を 損 害 し 」、\nかつ、\n  「 法 律 、行 政 法 規 に お け る 強 制 性 の 規 定 に 反 す る 」と 主 張 し 、人 民\n法院に訴訟を提起し、畢加索社と芸想社との間で締結した「商標許諾使\n\n用 契 約 」 が 無 効 で あ り 、 両 者 が 共 同 で 帕 弗 洛 社 の 経 済 損 失 100 万 元 を 賠\n償することを命じるよう請求した。上海市第一中級人民法院 は、係争商\n\n標 の 使 用 許 諾 契 約 は 双 方 当 事 者 の 真 実 な 意 思 表 明 に 該 当 し 、そ の 目 的 は\n\n係 争 商 標 の 独 占 許 諾 使 用 権 を 取 得 す る た め で あ り 、帕 弗 洛 社 の 合 法 的 利\n益を損害した主観的な悪意があると認定するのが難しく、\n                         「 商 標 法 」司 法\n解 釈 第 3 条 第 1 号 の 内 容 は 、「 商 標 法 」 に 規 定 す る 商 標 使 用 許 諾 方 法 の\n\n定義に該当し、強制性の法律規範に該当せず、係争契約の締結は法律・\n行政法規の強制性の規定に違反しないと判定した。したがって、帕弗洛\n社の全部の訴訟上の請求を棄却する判決を言い渡した。帕弗洛社、芸想\n\n社は、何れも不服として上訴を提起した。上海市 高級人民法院は、畢加\n索 社 と 芸 想 社 と の 間 で 係 争 商 標 の 使 用 許 諾 契 約 を 締 結 し た と き 、何 れ も\n\n帕弗洛社と畢加索社との間にすでに係争商標の独占使用許諾関係が存\n在 す る こ と を 知 得 し て い た の で 、芸 想 社 は 後 で 許 諾 さ れ た 善 意 の 第 三 者\n\n76\n\fに は 該 当 し な い も の の 、芸 想 社 に 帕 弗 洛 社 に 加 害 し よ う し た 主 観 的 悪 意\nが あ る こ と を 証 明 で き る 十 分 な 証 拠 が な く 、畢 加 索 社 と 芸 想 社 と の 間 に\n\n気 脈 を 通 じ 合 っ た 行 為 が 存 在 す る こ と を 証 明 で き る 証 拠 も な い の で 、か\n\nかる契約行為を悪意で気脈を通じ合って第三者の利益を損なった行為\nとして認定することができないと判定した。しかし、芸想社が善意の第\n\n三 者 に 該 当 せ ず 、帕 弗 洛 社 が 係 争 商 標 に 対 し て 享 有 す る 独 占 許 諾 使 用 権\n\nは、以降の係争商標の使用許諾契約関係に対して対抗できるので、畢加\n索社は、事実上、係争商標の使用許諾契約の義務を履行しておらず、芸\n想社も当該係争契約に基づいて係争商標の使用権を得ることができな\n\nい。してがって、人民法院 は、上訴を棄却し、原判決を維持する判決を\n言い渡した。\n ポイント解説\n\n本 事 件 の 二 審 判 決 に お い て 、人 民 法 院 は 、\n                                    「 契 約 法 」に 規 定 す る「 悪 意\nで 気 脈 を 通 じ 合 っ て 第 三 者 の 合 法 的 利 益 を 損 害 し た 」場 合 を 構 成 す る 場\n合、被告に主観的に加害した故意があることを証明するだけではなく、\n客 観 的 に 結 託 し 、気 脈 を 通 じ た 行 為 が あ る こ と も 証 明 し な け れ ば な ら な\nいと判定した。本事件において、以降の商標の独占使用許諾契約は、以\n降で締結されたことにより無効契約として認定されるわけには行かな"
}