{
  "source_id": "report_201701",
  "source_file": "report_201701.txt",
  "chunk_index": 21,
  "char_count": 3051,
  "text": "2010          2011        2012        2013    2014     2015\n                       年           年             年         年       年        年\n\n知的財産権侵害             1,294         3,134        7,840      5,021    5,242    4,913\n\n罪事件\n\n偽造粗悪商品生                596          774        2,607      2,455    3,966    3,925\n産販売罪事件\n\n不法経営罪事件             2,078         1,747        2,587      1,686    1,697    1,923\n\nその他の犯罪                     24          52            70     169      183      214\n\n合計                  3,992         5,707       13,104      9,331   11,088   10,975\n\n45\n\f図 Ⅰ － 1 1：2015 年 度 知 的 財 産 権 に 関 す る 刑 事 第 一 審 訴 訟 事 件 の 新 受 件 数\nの種類別割合図\n\nその他の犯罪\n                                     1.95%\n\n不法経営\n                                                      知識産権侵害罪事件\n                罪事件\n                17.52%\n                                                      偽造粗悪商品生産販売罪事\n                              知識産権侵害罪                 件\n                               事件 44.77%              不法経営罪事件\n          偽造粗悪商品生\n          産販売罪事件                                      その他の犯罪\n            35.76%\n\n表 Ⅰ -11   各年度の知的財産権に関する刑事一審訴訟事件の\n\n既 済 件 数 (種 類 別 )\n\n2010         2011      2012      2013    2014     2015\n                         年         年         年         年       年        年\n\n知的財産権侵害事\n                     1,254        2,967      7,684    4,957    5,103    4,856\n 件\n\n偽粗悪品生産販売\n                         609        750      2,504    2,390    3,856    3,965\n 罪事件\n\n不法経営罪事件             2,054        1,735      2,535    1,712    1,663    1,844\n\nその他の犯罪事件                    25        52        71     153      181      144\n\n合計                  3,942        5,504     12,794    9,212   10,803   10,809\n\n46\n\f  表 Ⅰ -12 各 年 度 の 知 的 財 産 権 侵 害 事 件 に 関 す る 刑 事 一 審 訴 訟 事 件 の\n                             判 決 結 果 (罪 名 別 )\n\n2010         2011       2012             2013       2014          2015\n\n年            年          年                年          年             年\n\n登録商標冒用罪                 585        1,060      2,012            1,546      2,031         2,133\n\n登録商標冒用商\n                        345          863      1,906            1,496      1,903         1,789\n品販売罪\n\n不法製造された\n登録商標標章の                 182          370        615              350        397           358\n\n不法製造販売罪\n\n専利詐称罪                        2            1         63                1          1             1\n\n著作権侵害罪                     85        594      3,018            1,499        722           523\n\n権利侵害複製品\n                             5          30          27              15         12              5\n販売罪\n\n営業秘密侵害罪                    50           49          43              50         37            47\n\n図 Ⅰ － 1 2： 全 国 の 地 方 人 民 法 院 の 知 的 財 産 権 に 関 す る\n\n刑事一審、二審事件のデータ\n    12000            11088 10975\n\n10000     9331\n\n8000\n\n2013\n     6000\n                                                                                 2014\n                                                                                 2015\n     4000\n\n2000\n                                              662        573     790"
}