{
  "source_id": "CV_20251208_29-0001_1",
  "source_file": "CV_20251208_29-0001 (1).txt",
  "chunk_index": 14,
  "char_count": 2406,
  "text": "している。つまり、一般国民は社会信用                が常に国民の健康と安全を脅かし、一時は海外\n     システムの不備を知りながらも、社会環                においても、中国から有毒な餃子、粉ミルク、\n     境の改善の必要性を確実に実感しており、               野菜などが輸出されたなどとする報道がなされ\n     社会信用システムを高く評価しているの                た。このような状況に対し、厳格な対応を含め\n     である。                              た改善措置を講じなければ、民衆の不満を抑え\n                                       きれず、国際社会でのイメージも大きく損なう\n こうした中国国民の反応については、中国国                  おそれが出始めていたのである。\n民にとっての社会信用システムの必要性や、中                   これらの問題解決のために、公安局や検察院\n国国民が求める個人情報とプライバシー権の保                  などの政府や司法部門が犯罪者に対して厳しい\n護のあり方といった側面を考察する必要があ                   対応を採るようになったが、十分な効果は見ら\nる。                                     れなかった。厳正に取り締まる法律はあるもの\n                                       の、脱法行為も存在した。こうした経済的な不\n（1）国民のムード                              正行為や非倫理的行為は、規模や範囲が限定的\n 中国国民は、社会信用システムに対して、三                  な場合、刑事案件にならないまま、多くの地域\nつの効果を期待している。                           で国民の日常生活に直接的な弊害を与えてい\n 第一に、治安強化と犯罪の防止である。社会                  た。一般国民からすれば、もし社会信用システ\nにおける犯罪率が急激に上昇していることに対                  ムが罰則をはじめとする、実効的な機能を備え\nして   liii\n            、歴代の中国政府は「厳打」のような臨         て活用され、司法機関の不足を補填することが\n時制裁措置を導入した。しかし、一時的な効果                  可能ならば、司法機関のみに頼る現状と比べて、\nはあるものの、根本的な問題解決には至らな                   もっと効果的になりうる。これも踏まえると、\nかった。国民が不満と不安を覚える中で、政府                  国民が社会信用システムを擁護するのは至極自\nに対する不信も高まることになったのである。                  然なことであるといえる。\n中国政府はこのような状況を受け、2004 年か                 第三は、行政機関と司法機関の信用性の回復\nら 2020 年まで「全地域を覆い、死角を無くす」              である。つまり、国民は共産党幹部の職権乱用\nをスローガンに最先端情報技術を用いた犯罪防                  や公的資金の流用、賄賂などといった犯罪に対\n止のための対策を掲げた。「平安城市」\n                 、「天網                  する取締りも期待しているのである。近年、共\n工程」および「雪亮工程」の三つの社会監視                   産党幹部による犯罪が各地で増加し、民衆の不\nシステムの構築に力を注いだのである。その                   満が抑えきれない状況になりつつある。司法機\n結果、2018 年時点で、暴行事件は 2012 年より            関が厳しく規制しているにもかかわらず、各地\n51.8% 減少し、重大交通事故の発生率は 43.8%            での犯罪は依然として途絶できていない。特\n減少した。社会の治安に対する人々の満足度が                  に、地方や中央政府の高級幹部による汚職や犯\n2012 年の 87.5% から、2017 年の 95.55% へとアッ   罪は、社会に深刻な悪影響を与えており、一般\nプしたという報道もなされている liv。                   国民も憤りを感じている lv。司法手段を通して\n 第二に、偽造商品の流通の途絶である。改革・                 の制裁は強く期待されているが、それでもこの\n開放以来、市場規模の拡大が急速に進んだが、                  ような犯罪を途絶することはできない。加え\n各種規制や法律の整備の進捗は相対的に緩慢で                  て、一般の犯罪者が法的制裁から逃れる事例も\nあった。さらに、拝金主義の風潮とビジネスに                  多い。このような現状も中国国民が社会信用シ\nおける不正行為によって、国民生活に直接かか                  ステムへの期待を高めた一因である。\nわりのあるさまざまな商品の偽造問題が頻発し\nた。偽造医薬品、偽造食品、偽の日常用品など\n\f16                             伊    夢瑛"
}