{
  "source_id": "from-datafication-to-data-state-making-sense-of-chinas-social-credit-system-and-",
  "source_file": "from-datafication-to-data-state-making-sense-of-chinas-social-credit-system-and-its-implications.txt",
  "chunk_index": 52,
  "char_count": 1084,
  "text": "Most of the MOUs and legislation concerning combined punishments include a\n               mechanism called “credit repair” (xinyong xiufu 信用修复), which allows individuals to\n               request that their names be removed from blacklists and that the restrictions imposed on\n               them be lifted.65 According to a national policy issued in late 2019, citizens can take\n               such measures to repair their credit as correcting “wrong conduct,” offering “pro bono\n               services” and engaging in “charity activities.”66 The policy behind this mechanism\n               appears to be that these behaviors can partly remedy the harm caused by law breaking\n               or other kinds of misconduct. Yet this arrangement may reproduce social inequalities, as\n               those with superior economic or social capital are better able to undertake the\n               prescribed charity activities and thereby appear less frequently on blacklists and/or\n               achieve higher social credit scores. It is also doubtful that the prescribed “reparative”"
}