{
  "source_id": "Hobbling_Big_Brother_Top-Level_Design_and_Local_Discretion_in_China_s_Social_Cre",
  "source_file": "Hobbling Big Brother: Top-Level Design and Local Discretion in China’ s Social Credit System.txt",
  "chunk_index": 24,
  "char_count": 2069,
  "text": "56. Kjeld Erik Brødsgaard, “Fragmented Authoritarianism or Integrated Fragmentation?” in Chinese\nPolitics as Fragmented Authoritarianism: Earthquakes, Energy and Environment, ed. Kjeld Erik Brødsgaard\n(New York: Routledge, 2017), 38–55.\n    57. Shiuh-Shen Chien, “Local Responses to Globalization in China: A Territorial Restructuring Process\nPerspective,” Paciﬁc Economic Review 13, no. 4 (2008): 508–9.\n    58. Wang Tao, “Zhaozhun wenti yuantou, genzhi ‘lanzheng daizheng’” [Identify the source of the prob-\nlem and cure the cadres’ “indolence, sloppiness, and neglect of their duties”], Renmin wang [People’s Daily\nOnline], August 30, 2016, http://dangjian.people.com.cn/n1/2016/0830/c117092-28676535.html, accessed\nNovember 12, 2020.\n\f20 •   T H E C H I N A J O U R N A L , No. 86, July 2021\n\nsocial credit will cross an invisible line drawn by their superiors and they will be\npunished. Therefore, progress in this area is extremely limited.\n    Our conclusions regarding City Z may not necessarily apply to all counties\nand cities in China. Some local governments might have received more support\nfrom their superiors and as a result may have made a breakthrough in imple-\nmenting the personal social credit system. However, we believe City Z does re-\nﬂect the rational choices made by most cities in China’s eastern coastal region\nregarding the social credit system, since they are under pressure to advance eco-\nnomic development and to minimize their own political risk. The regime under\nXi Jinping seems intent on continuing its efforts to set up a comprehensive sys-\ntem for monitoring all aspects of society. However, given local cadres’ awareness\nof the political risks involved, it may be a long time before the national author-\nities achieve that goal.\n\fCopyright of China Journal is the property of The Australian National University and its\ncontent may not be copied or emailed to multiple sites or posted to a listserv without the\ncopyright holder's express written permission. However, users may print, download, or email\narticles for individual use."
}