{
  "source_id": "Old_Regulatory_Wine_in_a_New_Bottle_of_Technology--A_Critical_Ana",
  "source_file": "Old Regulatory Wine in a New Bottle of Technology--A Critical Ana.txt",
  "chunk_index": 17,
  "char_count": 2982,
  "text": "administration according to law (rule of administrative law).31 The\n                                    scope of honesty and credibility includes two aspects. The first\n                                    concerns information disclosure, namely that the information\n                                    disclosed by administrative agencies should be complete, accurate,\n                                    and true. This requirement intends to solve the problem of\n                                    information disclosure and access during interactions between\n                                    private and public parties. The second aspect is to protect the\n                                    legitimate expectations of private parties through predictable\n                                    application of policies. Without good cause and passing through\n                                    proper legal procedure, administrative agencies cannot revoke or\n                                    change administrative decisions that have already been in effect; if an\n                                    administrative decision needs to be revoked or changed due to\n                                    national interests, public interests, or other legal causes, that decision\n                                    shall be made according to appropriate legal authority and procedures,\n                                    and any property loss thus suffered by a private party shall be\n                                    compensated according to law.32 This requirement is to enhance the\n                                    stability and predictability of policy and administrative decision-\n                                    making. Ten years later, the OCSCS further expanded the concept of\n                                    governmental integrity to include the principle of public\n                                    administration according to law itself (rule of administrative law),\n                                    with the focus on honoring agreements and keeping service\n                                    commitments, such as implementation of economic and social\n                                    development aspirations, as well as keeping commitments in\n                                    handling affairs of the general public. The integrity of civil servants\n                                    is also an integral part of governmental integrity. 33 Although the\n                                    central government is working hard to enhance the level of\n                                    governmental integrity in all localities, its evaluation obviously\n                                    depends on the institutional guarantee of legal liability, political\n                                    accountability, and administrative responsibility, and cannot be\n                                    evaluated through simple index and points diagrams."
}