{
  "source_id": "ssrn-2992537",
  "source_file": "ssrn-2992537.txt",
  "chunk_index": 24,
  "char_count": 2416,
  "text": "77\n    See for example Art.18, Hangzhou Rules; Art. 21, para. 1, Hubei Regulations.\n78\n    Art. 10(3), ‘Zhengwu xinxi ziyuan gongxiang guanli zanxing banfa’ (Interim Measures on the Sharing\nof Government Information Resources) (issued by State Council on September 5, 2016). According to the\nMeasures, information resources generated or collected by government agencies in the course of discharging\ntheir responsibilities should generally be subject to sharing with other agencies. Exempting information from\nsharing is only warranted by ‘laws, administrative regulations or policies made by the Central Committee of the\nChinese Communist Party or the State Council.’(Art. 10 (1)). In particular, ‘information resources concerning the\nsame theme of economic and social development and generated by various agencies together’ should be shared\ninter-departmentally through the sharing platforms at different levels. Credit information is a highlighted\nexample of such resources. (Art.10 (3)).\n79\n    Part V, Section 1, ‘Guowuyuan Bangongting Guanyu jiaqiang geren chengxin tixi jianshe de zhidao yijian’\n(Guiding Opinions of the General Office of State Council on Strengthening the Construction of the System for\nIndividual Integrity) (issued on December 23, 2016) (hereinafter Guidelines on Individual Integrity).\n80\n    Yuandian Credit, ‘2016 zhongguo shehui xinyong tixi quanjing baogao’ (Annual Report on China’s Social\nCredit System Construction) (Yuandian Xinyong Wang, January 2017) at 7, available at: <http://yuandiancredit.\ncom/h-nd-1312-2_347.html>; ‘Wowei youguan fuzeren jiu “cujin shuju fazhan xingdong gangyao” da jizhe wen’\n(Officials in the National Development and Reform Commission Receives Interview on The Action Outline for\nBig Data Development) (The SDPC’s Website, September 2015), available at: <http://www.sdpc.gov.cn/zcfb/\njd/201509/t20150925_752279.html>; The Big Data Outline set the target of installing a unified data exchange\nplatform by 2018 to cover all government departments at the central level. See Part III, Section I(1) of the Outline.\n81\n    See for example Art. 18, Shanghai Rules; Art. 27, Wuxi Regulations; Art. 24, Hubei Regulations.\n82\n    Ibid\n                                                                                              JCL 12:2          367\n\nElectronic copy available at: https://ssrn.com/abstract=2992537\n\fThe Transparent Self under Big Data Profiling"
}