{
  "source_id": "171212_China_Monitor_43_Social_Credit_System_Implementation",
  "source_file": "171212_China_Monitor_43_Social_Credit_System_Implementation.txt",
  "chunk_index": 19,
  "char_count": 2436,
  "text": "Focus 1: Getting different actors to share their data\nThe Social Credit System is a massive and complex project that will require many\ndifferent government agencies to coordinate their work practices with one anoth-                        A large number of bureaucracies are involved in setting up the Social Credit Sys-\ner. At the national level, the government has issued plans for division of labor until                  tem on the government side. The key to making the Social Credit System work is\n2020 covering twelve main areas subdivided into 84 sub-areas of responsibility,                         ensuring proper flow and accessibility of information. One of the greatest road-\nall of which are major policy projects requiring a high degree of synchronization.20                    blocks is getting these different actors to work together to make sure that an\n       The current implementation process can roughly be divided into two tracks:                       individual or entity who has defaulted (or stood out positively) in one area will\none, creating an overall nationwide framework for assessing both financial credit                       also be punished (or rewarded) in others.21 A study on the development of the\nand moral integrity (new laws and regulations, institutionalizing basic structures                      Social Credit System conducted by Qianhai Credit and the Liaowang Institute (a\nfor cooperation, setting common standards) and, two, experimenting with provin-                         think tank under the Xinhua news agency) has noted that reduplication of efforts\ncial, sectoral, and commercial pilots.                                                                  is inevitable, and might impede the progress of the system’s establishment if gov-\n                                                                                                        ernment and private organizations fail to adequately consult with one another\n                                                                                                        and share data.22 To address this lack of coordination, several mechanisms are cur-\n                                                                                                        rently being put into place.\nFigure 3\n\nMajor steps towards setting up a nationwide Social Credit System\n   Timeline of events, pilot projects, and policy documents ( )"
}