{
  "source_id": "the-impacts-of-china-s-shadow-banking-credit-creation-on-the-54osxc1mim",
  "source_file": "the-impacts-of-china-s-shadow-banking-credit-creation-on-the-54osxc1mim.txt",
  "chunk_index": 19,
  "char_count": 2370,
  "text": "Finally, we use a vector autoregressive statistical analysis to estimate the impact that the rate of shadow\nbanking deposits has had on monetary policy goals. The Granger Causality test indicates that the growth\nrate of shadow banking deposits has Granger Causality for the growth rates of the broad money supply,\nGDP, and the CPI. The impulse response analysis indicates shows that shadow bank deposits have an initial\npositive impact on the money supply implying a multiplicative effect during an expansion and a dampening\nimpact during a contraction. Later impacts are not statistically significant, which merits further study.\nConsistent with the CC-LM model, the impulse response analysis indicates that shadow bank deposits\npositively impact GDP with a lag of four periods. The impulse response analysis did not find a statistically\nsignificant effect of RSB on RCPI. The variance decomposition analysis indicated that RSB, along with\nRGDP and RCP, had a negligible impact on the RM2, indicating that the broad money supply is endogenously\ndetermined. The variance decomposition showed that RSB explains approximately 7% of the variance of\nRGDP and a negligible amount of the RCPI variance.\n\nOur results are consistent with the previous studies (Liu et al.,2019), indicating that shadow banking may be\na powerful amplification mechanism that impairs monetary policy transmission and reduces its effectiveness.\nWe find that shadow banking can have a multiplicative effect during expansions and a dampening effect\nduring slowdowns, which increases the uncertainty of monetary policy. Regulation seeks to strike the right\nbalance between the costs and benefits of policy intervention. Future research can determine the type of\nshadow bank regulation that would promote coordinated monetary policy and increased economic stability\nwithout stunting economic growth.\n                                                                                                                             44\n                                                                                                                             Page\n\nPeer-reviewed Academic Journal published by SSBFNET with respect to copyright holders.\n\f             Zhang et al. / International Journal of Finance & Banking Studies, Vol 9 No 4, 2020\n                                            ISSN: 2147-4486"
}