{
  "source_id": "Planning_Outline_for_the_Construction_of_a_Social_Credit_System_2014-2020",
  "source_file": "Planning Outline for the Construction of a Social Credit System (2014-2020).txt",
  "chunk_index": 10,
  "char_count": 2710,
  "text": "Credit construction in the area of finance. Innovate financial credit products, improve financial services, safeguard the security of personal\n      information of financial consumers, and protect the lawful rights and interests of financial consumers. Strengthen punishment of financial\n      swindles, malicious evasion of loan repayments, insider trading, selling fake warranties, insurance and compensation fraud, disclosure of\n      false information, illegal fundraising, obtaining foreign currency under false pretences and other acts of financial trust-breaking, and\n      standardize the order of financial markets. Strengthen the construction of financial credit information infrastructure, further broaden the\n      coverage of credit records, and strengthen the incentivizing role of the financial sector to those keeping trust, and its constraining role\n      towards trust-breakers.\n\nCredit construction in the area of taxation. Establish intra-departmental credit information sharing mechanisms. Launch the exchange,\n      verification and application of basic information about taxpayers, all kinds of trading information, asset ownership and transfer information\n      as well as taxation records and other such tax-related kinds of information. Further perfect tax payment information ranking evaluation and\n      publication systems, strengthen credit categorization management in the area of taxation, and give rein to the role of credit evaluation\n      differentials in rewarding or punishing taxpayers. Establish black-list systems for legal violations concerning taxation. Move forward the\n      joint management of taxation information and other kinds of social information, and ensure that taxpayers comply with fiscal law.\n\nCredit construction in the area of pricing. Guide enterprises and businesses to strengthen self-discipline in pricing, standardize and guide\n      businesses’ pricing acts, implement systems for businesses to clearly indicate their prices and fees, and strive for “clear real prices”.\n      Supervise and urge businesses in strengthening internal pricing management, establish and complete internal pricing management systems\n      on the basis of the condition of the business. Perfect business pricing sincerity systems, complete information disclosure work, and\n      promote realistic reward and punishment systems. Strengthen pricing law enforcement inspection and anti-monopoly law enforcement,\n      investigate and prosecute the concoction and dissemination of price-rising information, pricing swindles, pricing monopolies and other\n      such trust-breaking activities in pricing, openly expose model cases, and standardize the market pricing order."
}